<archimate:ArchimateDiagramModel
    xmlns:xsi="http://www.w3.org/2001/XMLSchema-instance"
    xmlns:archimate="http://www.archimatetool.com/archimate"
    name="Voorzieningen naar laag (oud)"
    id="id-b5a28537db58418f83ff1cfd9aac3905"
    viewpoint="application_cooperation">
  <children
      xsi:type="archimate:DiagramModelNote"
      id="id-c2b412d159ec4ba8a31388c1d25f6c94"
      textAlignment="1"
      content="Of wordt dit business functie: diploma verstrekken, verzuim rapporteren in keten, door voorziening of RC gerealiseerd (welke voorziening/RC dan)">
    <sourceConnections
        id="id-26dac40fe787469b887630b44ad64766"
        source="id-c2b412d159ec4ba8a31388c1d25f6c94"
        target="id-177de66f94a44a8c918d622df84df7ec"/>
    <sourceConnections
        id="id-11d68b21b0d44eee968b3001dc200d60"
        source="id-c2b412d159ec4ba8a31388c1d25f6c94"
        target="id-c8ff0078803246909c5684b0f25f855b"/>
    <bounds
        x="-96"
        y="-174"
        width="185"
        height="104"/>
  </children>
  <children
      xsi:type="archimate:DiagramModelNote"
      id="id-e2ab5177d19e407e9f432a2a337c7157"
      textAlignment="1"
      content="Naar plaatje uit architectuurdocument edukoppeling. Mogelijk zijn dit geen IV domeinen die we willen onderkennen maar eerder &quot;lagen&quot;. ">
    <bounds
        x="984"
        y="468"
        width="185"
        height="169"/>
  </children>
  <children
      xsi:type="archimate:DiagramModelNote"
      id="id-20a7f20d36c24efbafa9ff9fa3f2c93f"
      textAlignment="1"
      content="wat mij betreft een register">
    <bounds
        x="1296"
        y="-252"
        width="109"
        height="85"/>
  </children>
  <children
      xsi:type="archimate:DiagramModelArchimateObject"
      id="id-177de66f94a44a8c918d622df84df7ec"
      targetConnections="id-26dac40fe787469b887630b44ad64766"
      font="1|Segoe UI|9.0|1|WINDOWS|1|-12|0|0|0|700|0|0|0|0|3|2|1|34|Segoe UI">
    <bounds
        x="156"
        y="-252"
        width="169"
        height="55"/>
    <archimateElement
        xsi:type="archimate:ApplicationComponent"
        href="ApplicationComponent_id-6c09a88c1595477586afbc3c2ae039d7.xml#id-6c09a88c1595477586afbc3c2ae039d7"/>
  </children>
  <children
      xsi:type="archimate:DiagramModelArchimateObject"
      id="id-c8ff0078803246909c5684b0f25f855b"
      targetConnections="id-11d68b21b0d44eee968b3001dc200d60"
      font="1|Segoe UI|9.0|1|WINDOWS|1|-12|0|0|0|700|0|0|0|0|3|2|1|34|Segoe UI">
    <bounds
        x="360"
        y="-252"
        width="169"
        height="55"/>
    <archimateElement
        xsi:type="archimate:ApplicationComponent"
        href="ApplicationComponent_id-5d3c1ea7c0724adcaf20f9e1cdf3e23b.xml#id-5d3c1ea7c0724adcaf20f9e1cdf3e23b"/>
  </children>
  <children
      xsi:type="archimate:DiagramModelArchimateObject"
      id="id-3f0d16953f6f43f7a86a617d935d3913"
      font="1|Segoe UI|9.0|1|WINDOWS|1|-12|0|0|0|700|0|0|0|0|3|2|1|34|Segoe UI">
    <bounds
        x="576"
        y="-252"
        width="169"
        height="55"/>
    <archimateElement
        xsi:type="archimate:ApplicationComponent"
        href="ApplicationComponent_6547e24b-b439-41f7-9ef8-32e2d8708068.xml#6547e24b-b439-41f7-9ef8-32e2d8708068"/>
  </children>
  <children
      xsi:type="archimate:DiagramModelArchimateObject"
      id="id-4f7922b710ce49d5affdf95aece9d80e"
      font="1|Segoe UI|9.0|1|WINDOWS|1|-12|0|0|0|700|0|0|0|0|3|2|1|34|Segoe UI">
    <bounds
        x="788"
        y="-252"
        width="169"
        height="55"/>
    <archimateElement
        xsi:type="archimate:ApplicationComponent"
        href="ApplicationComponent_cffdc104-0654-4072-ac0e-3c8ee57be7f9.xml#cffdc104-0654-4072-ac0e-3c8ee57be7f9"/>
  </children>
  <children
      xsi:type="archimate:DiagramModelArchimateObject"
      id="id-ea463a7a1282450ebf56b6aa2e99d3e7"
      font="1|Segoe UI|9.0|1|WINDOWS|1|-12|0|0|0|700|0|0|0|0|3|2|1|34|Segoe UI">
    <bounds
        x="144"
        y="-150"
        width="169"
        height="55"/>
    <archimateElement
        xsi:type="archimate:ApplicationComponent"
        href="ApplicationComponent_id-c15735c77a7b463e8ba60f1451820708.xml#id-c15735c77a7b463e8ba60f1451820708"/>
  </children>
  <children
      xsi:type="archimate:DiagramModelArchimateObject"
      id="id-5943bb0b59d0412dbb74f929c28e9965"
      font="1|Segoe UI|9.0|1|WINDOWS|1|-12|0|0|0|700|0|0|0|0|3|2|1|34|Segoe UI">
    <bounds
        x="360"
        y="-156"
        width="169"
        height="55"/>
    <archimateElement
        xsi:type="archimate:ApplicationComponent"
        href="ApplicationComponent_eca3bdfe-03c6-467d-888b-9f22844970a6.xml#eca3bdfe-03c6-467d-888b-9f22844970a6"/>
  </children>
  <children
      xsi:type="archimate:DiagramModelArchimateObject"
      id="id-52e1297ec6704e319bb8c4718dc539d7">
    <bounds
        x="577"
        y="-156"
        width="168"
        height="55"/>
    <archimateElement
        xsi:type="archimate:ApplicationComponent"
        href="ApplicationComponent_469dd452-6189-469d-98a6-cb65b9448bd8.xml#469dd452-6189-469d-98a6-cb65b9448bd8"/>
  </children>
  <children
      xsi:type="archimate:DiagramModelArchimateObject"
      id="id-8ccd3c1e24c84d73beeef5dece1e5953"
      font="1|Segoe UI|9.0|1|WINDOWS|1|-12|0|0|0|700|0|0|0|0|3|2|1|34|Segoe UI">
    <bounds
        x="756"
        y="-156"
        width="169"
        height="55"/>
    <archimateElement
        xsi:type="archimate:ApplicationComponent"
        href="ApplicationComponent_2acc9a7f-0f05-4dd3-b4f5-b135eadd3861.xml#2acc9a7f-0f05-4dd3-b4f5-b135eadd3861"/>
  </children>
  <children
      xsi:type="archimate:DiagramModelArchimateObject"
      id="id-8d9b927f1f444fec9ef405a1fd7d0f4c"
      font="1|Segoe UI|9.0|1|WINDOWS|1|-12|0|0|0|700|0|0|0|0|3|2|1|34|Segoe UI">
    <bounds
        x="936"
        y="-156"
        width="169"
        height="55"/>
    <archimateElement
        xsi:type="archimate:ApplicationComponent"
        href="ApplicationComponent_id-e6d2edf853804f0a9572cd5e076a2d5d.xml#id-e6d2edf853804f0a9572cd5e076a2d5d"/>
  </children>
  <children
      xsi:type="archimate:DiagramModelArchimateObject"
      id="id-5decb3c7dbac4961b883f396476f9566"
      font="1|Segoe UI|9.0|1|WINDOWS|1|-12|0|0|0|700|0|0|0|0|3|2|1|34|Segoe UI">
    <bounds
        x="1116"
        y="-156"
        width="169"
        height="55"/>
    <archimateElement
        xsi:type="archimate:ApplicationComponent"
        href="ApplicationComponent_f0deee35-737b-4826-b4d0-62fe15f43646.xml#f0deee35-737b-4826-b4d0-62fe15f43646"/>
  </children>
  <children
      xsi:type="archimate:DiagramModelArchimateObject"
      id="id-2b02df4c3c844ca7bffdc6a7293e0711"
      font="1|Segoe UI|9.0|1|WINDOWS|1|-12|0|0|0|700|0|0|0|0|3|2|1|34|Segoe UI">
    <bounds
        x="156"
        y="-60"
        width="169"
        height="55"/>
    <archimateElement
        xsi:type="archimate:ApplicationComponent"
        href="ApplicationComponent_cabc4e6b-b63c-4eef-bedd-d86445b5cfa5.xml#cabc4e6b-b63c-4eef-bedd-d86445b5cfa5"/>
  </children>
  <children
      xsi:type="archimate:DiagramModelArchimateObject"
      id="id-a3abe9956e6c4d10b67c75b3de7be9c8"
      font="1|Segoe UI|9.0|1|WINDOWS|1|-12|0|0|0|700|0|0|0|0|3|2|1|34|Segoe UI">
    <bounds
        x="372"
        y="-60"
        width="169"
        height="55"/>
    <archimateElement
        xsi:type="archimate:ApplicationComponent"
        href="ApplicationComponent_3dc18325-40a3-454d-90d9-f12d2fee5616.xml#3dc18325-40a3-454d-90d9-f12d2fee5616"/>
  </children>
  <children
      xsi:type="archimate:DiagramModelArchimateObject"
      id="id-e90db20cb8444fb691fe748a9c39a358"
      font="1|Segoe UI|9.0|1|WINDOWS|1|-12|0|0|0|700|0|0|0|0|3|2|1|34|Segoe UI">
    <bounds
        x="577"
        y="-60"
        width="169"
        height="55"/>
    <archimateElement
        xsi:type="archimate:ApplicationComponent"
        href="ApplicationComponent_id-63c4b95f718346e39258957073cb424d.xml#id-63c4b95f718346e39258957073cb424d"/>
  </children>
  <children
      xsi:type="archimate:DiagramModelArchimateObject"
      id="id-e503cf00f2c8435a99598bf3f881c744"
      font="1|Segoe UI|9.0|1|WINDOWS|1|-12|0|0|0|700|0|0|0|0|3|2|1|34|Segoe UI">
    <bounds
        x="768"
        y="-72"
        width="169"
        height="55"/>
    <archimateElement
        xsi:type="archimate:ApplicationComponent"
        href="ApplicationComponent_fe7e3e00-ff95-48e9-9db5-80eaf22852dd.xml#fe7e3e00-ff95-48e9-9db5-80eaf22852dd"/>
  </children>
  <children
      xsi:type="archimate:DiagramModelArchimateObject"
      id="id-93fd49b5fdb94750bba0ea1513f726bf"
      font="1|Segoe UI|9.0|1|WINDOWS|1|-12|0|0|0|700|0|0|0|0|3|2|1|34|Segoe UI">
    <bounds
        x="972"
        y="-72"
        width="169"
        height="55"/>
    <archimateElement
        xsi:type="archimate:ApplicationComponent"
        href="ApplicationComponent_81b76a67-505c-4c5b-a5cd-e95036f1abf7.xml#81b76a67-505c-4c5b-a5cd-e95036f1abf7"/>
  </children>
  <children
      xsi:type="archimate:DiagramModelArchimateObject"
      id="id-ebec234b754d46fe9a7a8f8bee2ab467"
      font="1|Segoe UI|9.0|1|WINDOWS|1|-12|0|0|0|700|0|0|0|0|3|2|1|34|Segoe UI">
    <bounds
        x="156"
        y="36"
        width="169"
        height="55"/>
    <archimateElement
        xsi:type="archimate:ApplicationComponent"
        href="ApplicationComponent_ad1f7241-de7f-4206-92cb-04075efd117a.xml#ad1f7241-de7f-4206-92cb-04075efd117a"/>
  </children>
  <children
      xsi:type="archimate:DiagramModelArchimateObject"
      id="id-0f37fcdf12c542fdb8381c3eab596779"
      font="1|Segoe UI|9.0|1|WINDOWS|1|-12|0|0|0|700|0|0|0|0|3|2|1|34|Segoe UI">
    <bounds
        x="372"
        y="24"
        width="169"
        height="55"/>
    <archimateElement
        xsi:type="archimate:ApplicationComponent"
        href="ApplicationComponent_d765f090-d4dd-44db-b378-bf9d87b7c5bd.xml#d765f090-d4dd-44db-b378-bf9d87b7c5bd"/>
  </children>
  <children
      xsi:type="archimate:DiagramModelArchimateObject"
      id="id-4abba7ee55d34ba3bd7c01dbe736e846"
      font="1|Segoe UI|9.0|1|WINDOWS|1|-12|0|0|0|700|0|0|0|0|3|2|1|34|Segoe UI">
    <bounds
        x="144"
        y="192"
        width="169"
        height="55"/>
    <archimateElement
        xsi:type="archimate:ApplicationComponent"
        href="ApplicationComponent_311e4227-c0f4-4751-808d-c22d903e34cb.xml#311e4227-c0f4-4751-808d-c22d903e34cb"/>
  </children>
  <children
      xsi:type="archimate:DiagramModelArchimateObject"
      id="id-8e23f95d6d2c4e9f82738edd386f76f7"
      font="1|Segoe UI|9.0|1|WINDOWS|1|-12|0|0|0|700|0|0|0|0|3|2|1|34|Segoe UI">
    <bounds
        x="336"
        y="192"
        width="169"
        height="55"/>
    <archimateElement
        xsi:type="archimate:ApplicationComponent"
        href="ApplicationComponent_cf45b873-1f18-4be8-bede-52714accb248.xml#cf45b873-1f18-4be8-bede-52714accb248"/>
  </children>
  <children
      xsi:type="archimate:DiagramModelArchimateObject"
      id="id-d31700b8cf514ba789bb7c7606bf5e17"
      font="1|Segoe UI|9.0|1|WINDOWS|1|-12|0|0|0|700|0|0|0|0|3|2|1|34|Segoe UI">
    <bounds
        x="528"
        y="192"
        width="169"
        height="49"/>
    <archimateElement
        xsi:type="archimate:ApplicationComponent"
        href="ApplicationComponent_289f862e-68fc-4058-9bc1-1409c1614f44.xml#289f862e-68fc-4058-9bc1-1409c1614f44"/>
  </children>
  <children
      xsi:type="archimate:DiagramModelArchimateObject"
      id="id-b0e24a96c8834e5a91b5dce757fa4667">
    <bounds
        x="720"
        y="189"
        width="193"
        height="55"/>
    <archimateElement
        xsi:type="archimate:ApplicationComponent"
        href="ApplicationComponent_id-07d38004578f463c9950c904a561199e.xml#id-07d38004578f463c9950c904a561199e"/>
  </children>
  <children
      xsi:type="archimate:DiagramModelArchimateObject"
      id="id-87a934d3a70a4e9fbb5574d85e5375c8">
    <bounds
        x="937"
        y="216"
        width="168"
        height="55"/>
    <archimateElement
        xsi:type="archimate:ApplicationComponent"
        href="ApplicationComponent_b2e36464-485e-4816-b3fe-4a2280c1ddf6.xml#b2e36464-485e-4816-b3fe-4a2280c1ddf6"/>
  </children>
  <children
      xsi:type="archimate:DiagramModelArchimateObject"
      id="id-c1f1b7242a814fb896829578afc3043d"
      font="1|Segoe UI|9.0|1|WINDOWS|1|-12|0|0|0|700|0|0|0|0|3|2|1|34|Segoe UI">
    <bounds
        x="144"
        y="336"
        width="169"
        height="55"/>
    <archimateElement
        xsi:type="archimate:ApplicationComponent"
        href="ApplicationComponent_777dbf70-2edc-489a-97df-1941071b3453.xml#777dbf70-2edc-489a-97df-1941071b3453"/>
  </children>
  <children
      xsi:type="archimate:DiagramModelArchimateObject"
      id="id-8d40022e783b4e24a25e049788706c9e"
      font="1|Segoe UI|9.0|1|WINDOWS|1|-12|0|0|0|700|0|0|0|0|3|2|1|34|Segoe UI">
    <bounds
        x="336"
        y="336"
        width="169"
        height="55"/>
    <archimateElement
        xsi:type="archimate:ApplicationComponent"
        href="ApplicationComponent_6f1bac9a-f2df-4d81-8921-8a90c867740f.xml#6f1bac9a-f2df-4d81-8921-8a90c867740f"/>
  </children>
  <children
      xsi:type="archimate:DiagramModelArchimateObject"
      id="id-990c340e708449349c10e153810edeaa"
      font="1|Segoe UI|9.0|1|WINDOWS|1|-12|0|0|0|700|0|0|0|0|3|2|1|34|Segoe UI">
    <bounds
        x="528"
        y="336"
        width="169"
        height="55"/>
    <archimateElement
        xsi:type="archimate:ApplicationComponent"
        href="ApplicationComponent_3e1a21df-16f3-4301-828d-b17e1c2fbc29.xml#3e1a21df-16f3-4301-828d-b17e1c2fbc29"/>
  </children>
  <children
      xsi:type="archimate:DiagramModelArchimateObject"
      id="id-94118e0e5e2249778fdf090d51a174c5"
      font="1|Segoe UI|9.0|1|WINDOWS|1|-12|0|0|0|700|0|0|0|0|3|2|1|34|Segoe UI">
    <bounds
        x="720"
        y="336"
        width="169"
        height="55"/>
    <archimateElement
        xsi:type="archimate:ApplicationComponent"
        href="ApplicationComponent_5c38253d-b373-4c2c-8e93-de830ea496d4.xml#5c38253d-b373-4c2c-8e93-de830ea496d4"/>
  </children>
  <children
      xsi:type="archimate:DiagramModelArchimateObject"
      id="id-327600f6b82f4aaea2dc48d9c400f4bf"
      font="1|Segoe UI|9.0|1|WINDOWS|1|-12|0|0|0|700|0|0|0|0|3|2|1|34|Segoe UI">
    <bounds
        x="936"
        y="336"
        width="169"
        height="55"/>
    <archimateElement
        xsi:type="archimate:ApplicationComponent"
        href="ApplicationComponent_4cfca4f4-e927-4913-ab36-391942b03e58.xml#4cfca4f4-e927-4913-ab36-391942b03e58"/>
  </children>
  <children
      xsi:type="archimate:DiagramModelArchimateObject"
      id="id-98424b1deab34453ac3fc27b63a4b92b"
      font="1|Segoe UI|9.0|1|WINDOWS|1|-12|0|0|0|700|0|0|0|0|3|2|1|34|Segoe UI">
    <bounds
        x="1128"
        y="336"
        width="169"
        height="55"/>
    <archimateElement
        xsi:type="archimate:ApplicationComponent"
        href="ApplicationComponent_8c688307-2251-4f3c-bd7c-f9ed8faf3ae0.xml#8c688307-2251-4f3c-bd7c-f9ed8faf3ae0"/>
  </children>
  <children
      xsi:type="archimate:DiagramModelArchimateObject"
      id="id-ef81bf1056964de5a65b90776b766245"
      font="1|Segoe UI|9.0|1|WINDOWS|1|-12|0|0|0|700|0|0|0|0|3|2|1|34|Segoe UI">
    <bounds
        x="156"
        y="444"
        width="169"
        height="55"/>
    <archimateElement
        xsi:type="archimate:ApplicationComponent"
        href="ApplicationComponent_id-d570d818fc6846e39ed380c313999289.xml#id-d570d818fc6846e39ed380c313999289"/>
  </children>
  <children
      xsi:type="archimate:DiagramModelArchimateObject"
      id="id-d9c5071f542c4f77b951583728be8768"
      font="1|Segoe UI|9.0|1|WINDOWS|1|-12|0|0|0|700|0|0|0|0|3|2|1|34|Segoe UI">
    <bounds
        x="360"
        y="432"
        width="169"
        height="55"/>
    <archimateElement
        xsi:type="archimate:ApplicationComponent"
        href="ApplicationComponent_id-ad99f6e8c1a94d28b39603517fe91461.xml#id-ad99f6e8c1a94d28b39603517fe91461"/>
  </children>
  <children
      xsi:type="archimate:DiagramModelArchimateObject"
      id="id-8894e5277b114e179401d24c262238e8"
      font="1|Segoe UI|9.0|1|WINDOWS|1|-12|0|0|0|700|0|0|0|0|3|2|1|34|Segoe UI">
    <bounds
        x="168"
        y="552"
        width="169"
        height="55"/>
    <archimateElement
        xsi:type="archimate:ApplicationComponent"
        href="ApplicationComponent_4de38c5a-61de-4b14-8967-64fc51492928.xml#4de38c5a-61de-4b14-8967-64fc51492928"/>
  </children>
  <properties
      key="Publiceren"
      value="nee"/>
</archimate:ArchimateDiagramModel>
